fluent_compiler/__init__.py
fluent_compiler/ast_compat.py
fluent_compiler/builtins.py
fluent_compiler/bundle.py
fluent_compiler/codegen.py
fluent_compiler/compiler.py
fluent_compiler/errors.py
fluent_compiler/escapers.py
fluent_compiler/resource.py
fluent_compiler/runtime.py
fluent_compiler/types.py
fluent_compiler/utils.py
fluent_compiler-1.1.dist-info/LICENSE
fluent_compiler-1.1.dist-info/METADATA
fluent_compiler-1.1.dist-info/WHEEL
fluent_compiler-1.1.dist-info/top_level.txt
fluent_compiler-1.1.dist-info/RECORD
