Metadata-Version: 2.1
Name: fluent_compiler
Version: 1.1
Summary: Blazing fast implementation of Fluent localization language.
Home-page: https://github.com/django-ftl/fluent-compiler
Author: Luke Plant
Author-email: L.Plant.98@cantab.net
License: APL 2
Project-URL: Homepage, https://github.com/django-ftl/fluent-compiler
Project-URL: Documentation, https://fluent-compiler.readthedocs.io/en/latest/
Project-URL: Repository, https://github.com/django-ftl/fluent-compiler
Project-URL: Changelog, https://fluent-compiler.readthedocs.io/en/latest/history.html
Project-URL: Tracker, https://github.com/django-ftl/fluent-compiler/issues
Keywords: fluent,localization,l10n,compiler,projectfluent,ftl
Platform: UNKNOWN
Classifier: Development Status :: 5 - Production/Stable
Classifier: Intended Audience :: Developers
Classifier: License :: OSI Approved :: Apache Software License
Classifier: Operating System :: OS Independent
Classifier: Programming Language :: Python :: 3 :: Only
Classifier: Programming Language :: Python :: 3.7
Classifier: Programming Language :: Python :: 3.8
Classifier: Programming Language :: Python :: 3.9
Classifier: Programming Language :: Python :: 3.10
Classifier: Programming Language :: Python :: 3.11
Classifier: Programming Language :: Python :: 3.12
Classifier: Programming Language :: Python :: Implementation :: CPython
Classifier: Programming Language :: Python :: Implementation :: PyPy
Classifier: Topic :: Software Development :: Compilers
Classifier: Topic :: Software Development :: Libraries :: Python Modules
Classifier: Topic :: Software Development :: Localization
Requires-Python: >=3.7
License-File: LICENSE
